business_profile_yelp_local/__init__.py
business_profile_yelp_local/yelp_importer.py
business_profile_yelp_local-0.0.14.dist-info/METADATA
business_profile_yelp_local-0.0.14.dist-info/WHEEL
business_profile_yelp_local-0.0.14.dist-info/top_level.txt
business_profile_yelp_local-0.0.14.dist-info/RECORD
