Metadata-Version: 2.1
Name: business-profile-yelp-local
Version: 0.0.14
Home-page: https://github.com/circles-zone/business-profile-yelp-local-python-package
Author: Circles
Author-email: info@circles.life
Classifier: Programming Language :: Python :: 3
Classifier: License :: Other/Proprietary License
Classifier: Operating System :: OS Independent
Requires-Dist: gql >=3.4.0
Requires-Dist: requests >=2.29.0
Requires-Dist: requests-toolbelt >=0.10.1
Requires-Dist: logger-local >=0.0.71
Requires-Dist: python-sdk-remote
